pglift_cli/__init__.py
pglift_cli/__main__.py
pglift_cli/_settings.py
pglift_cli/_site.py
pglift_cli/base.py
pglift_cli/console.py
pglift_cli/database.py
pglift_cli/hookspecs.py
pglift_cli/instance.py
pglift_cli/main.py
pglift_cli/model.py
pglift_cli/patroni.py
pglift_cli/pgconf.py
pglift_cli/pghba.py
pglift_cli/pm.py
pglift_cli/postgres.py
pglift_cli/prometheus.py
pglift_cli/py.typed
pglift_cli/role.py
pglift_cli/util.py
pglift_cli/wal.py
pglift_cli/pgbackrest/__init__.py
pglift_cli/pgbackrest/repo_path.py
pglift_cli-2.6.1.dist-info/METADATA
pglift_cli-2.6.1.dist-info/WHEEL
pglift_cli-2.6.1.dist-info/entry_points.txt
pglift_cli-2.6.1.dist-info/RECORD
